crypto_sim/__init__.py
crypto_sim/crypto.py
crypto_sim-0.0.5.dist-info/LICENSE.txt
crypto_sim-0.0.5.dist-info/METADATA
crypto_sim-0.0.5.dist-info/WHEEL
crypto_sim-0.0.5.dist-info/top_level.txt
crypto_sim-0.0.5.dist-info/RECORD
