Metadata-Version: 2.1
Name: crypto-sim
Version: 0.0.5
Summary: A API for cryptography lib
Home-page: https://github.com/chetan0402/crypto-sim
Author: Chetan Sharma
Author-email: chetansharma67g@gmail.com
License: MIT
Platform: UNKNOWN
Classifier: Programming Language :: Python :: 3
Classifier: License :: OSI Approved :: MIT License
Classifier: Operating System :: OS Independent
Requires-Dist: cryptography (~=2.9.2)
